{
  "id": "bloomberg-terminal-ipo",
  "name": {
    "en": "Bloomberg Terminal - IPO Module",
    "zh": "彭博终端 - IPO模块"
  },
  "description": {
    "en": "Bloomberg Terminal's IPO (Initial Public Offering) module provides comprehensive data on equity offerings worldwide. This specialized module offers detailed information on IPO pricing, trading history, deal structures, and post-IPO performance tracking. Users can access pre-built and customized screens to research IPO data by various criteria including offer type, equity index, date range, and announcement dates. The module includes overview data, deal details, historical pricing, and volume information for global IPO markets, with export capabilities to Excel for further analysis.",
    "zh": "彭博终端的IPO（首次公开募股）模块提供全球股票发行的综合数据。该专业模块提供有关IPO定价、交易历史、交易结构和上市后业绩跟踪的详细信息。用户可以访问预构建和自定义筛选器，按各种标准研究IPO数据，包括发行类型、股票指数、日期范围和公告日期。该模块包括全球IPO市场的概览数据、交易详情、历史定价和成交量信息，并可导出到Excel进行进一步分析。"
  },
  "website": "https://www.bloomberg.com",
  "data_url": "https://www.bloomberg.com/professional/products/bloomberg-terminal/",
  "api_url": "https://www.bloomberg.com/professional/support/api-library/",
  "country": null,
  "domains": [
    "ipo",
    "equity offerings",
    "capital markets",
    "investment banking",
    "securities issuance"
  ],
  "geographic_scope": "global",
  "update_frequency": "real-time",
  "tags": [
    "ipo",
    "initial-public-offering",
    "equity-offerings",
    "新股发行",
    "首次公开募股",
    "上市公司",
    "股票发行",
    "招股",
    "pricing",
    "定价",
    "trading-history",
    "交易历史",
    "deal-structure",
    "capital-markets",
    "资本市场",
    "prospectus",
    "招股书",
    "underwriting",
    "承销",
    "post-ipo-performance",
    "上市后表现",
    "commercial",
    "subscription-based",
    "bloomberg",
    "terminal"
  ],
  "data_content": {
    "en": [
      "IPO deal overview and summary information",
      "Initial pricing data and offer price ranges",
      "Historical trading data and volume post-IPO",
      "Deal structure and underwriting details",
      "Pre-IPO and post-IPO performance metrics",
      "Searchable database by offer type, index, and date range",
      "Announcement dates and filing timelines",
      "Global IPO coverage across major exchanges (NYSE, NASDAQ, LSE, HKEX, etc.)",
      "Secondary offering data and follow-on transactions",
      "Comparable IPO analysis tools",
      "Underwriter league tables and market share",
      "Excel export functionality for custom analysis"
    ],
    "zh": [
      "IPO交易概览和摘要信息",
      "初始定价数据和发行价格区间",
      "上市后历史交易数据和成交量",
      "交易结构和承销详情",
      "上市前和上市后业绩指标",
      "按发行类型、指数和日期范围的可搜索数据库",
      "公告日期和申报时间表",
      "覆盖全球主要交易所的IPO数据（纽交所、纳斯达克、伦敦证交所、港交所等）",
      "二次发行数据和后续交易",
      "可比IPO分析工具",
      "承销商排行榜和市场份额",
      "Excel导出功能用于自定义分析"
    ]
  },
  "authority_level": "commercial"
}
