{
  "id": "moe-china",
  "name": {
    "en": "Ministry of Education of the People's Republic of China",
    "zh": "中华人民共和国教育部"
  },
  "description": {
    "en": "The Ministry of Education of the People's Republic of China (MOE) is the government department responsible for comprehensive education management nationwide. It formulates education policies, publishes education statistics, supervises educational institutions at all levels, and provides authoritative data on education development including enrollment, teacher staffing, infrastructure, and educational expenditure across China.",
    "zh": "中华人民共和国教育部是主管全国教育事业的国务院组成部门。负责制定教育政策、发布教育统计数据、监督管理各级各类教育机构,提供包括学生入学、师资配备、基础设施建设、教育经费等方面的权威教育发展数据。"
  },
  "website": "https://www.moe.gov.cn/",
  "data_url": "https://www.moe.gov.cn/jyb_xxgk/xxgk/neirong/tongji/",
  "api_url": null,
  "authority_level": "government",
  "country": "CN",
  "domains": [
    "education",
    "education-statistics",
    "education-policy",
    "higher-education",
    "basic-education"
  ],
  "geographic_scope": "national",
  "update_frequency": "annual",
  "tags": [
    "教育部",
    "ministry-of-education",
    "教育统计",
    "education-statistics",
    "教育事业发展",
    "education-development",
    "学校统计",
    "school-statistics",
    "学生数据",
    "student-data",
    "教师数据",
    "teacher-data",
    "教育经费",
    "education-expenditure",
    "高等教育",
    "higher-education",
    "基础教育",
    "basic-education",
    "职业教育",
    "vocational-education",
    "学前教育",
    "preschool-education",
    "教育政策",
    "education-policy",
    "教育法规",
    "education-regulations"
  ],
  "data_content": {
    "en": [
      "National education development statistics bulletin (annual comprehensive education data)",
      "Education statistics data (enrollment, graduates, school count, teacher staffing across all levels)",
      "China Education Monitoring and Evaluation Statistical Indicator System",
      "School (institution) code management data",
      "National education expenditure statistics (annual education funding execution data)",
      "Annual data on students studying abroad and international students in China",
      "Education policy documents and regulations",
      "Administrative licensing information",
      "Financial budgets and final accounts",
      "Government procurement information",
      "Personnel work information",
      "Education information disclosure annual reports",
      "Ministry of Education bulletins and briefings"
    ],
    "zh": [
      "全国教育事业发展统计公报(年度综合教育数据)",
      "教育统计数据(各级各类学校招生、毕业生、学校数量、教师配备等)",
      "中国教育监测与评价统计指标体系",
      "学校(机构)代码管理数据",
      "全国教育经费执行情况统计公告(年度教育经费投入数据)",
      "年度出国留学、来华留学数据",
      "教育政策文件与法规",
      "行政许可信息",
      "财政预算、决算信息",
      "政府采购信息",
      "人事工作信息",
      "教育信息公开年度报告",
      "教育部公报、简报"
    ]
  }
}
